{
  "cislo_konania_spisu": "OU-RS-OSZP-2025/019174",
  "cislo_rozhodnutia": null,
  "datum_dokumentu": null,
  "datum_zverejnenia": null,
  "lehoty_na_vyjadrenie": "5 pracovných dní od zverejnenia tejto informácie",
  "ziadatel_navrhovatel": "fyzická osoba",
  "miesto_realizacie": {
    "kraj": null,
    "okres": "Rimavská Sobota",
    "obec": "Klenovec",
    "katastralne_uzemia": [
      {
        "nazov": "Klenovec",
        "parcely": [
          {
            "typ": "E-KN",
            "cisla": [
              "6283"
            ]
          }
        ]
      }
    ],
    "nazov_lokality": null
  },
  "typ_dokumentu": "Zverejnenie informácie o začatí správneho konania",
  "typ_zasahu": [
    "výrub drevín",
    "čistenie pozemku"
  ],
  "typ_uzemia": [
    "neviem"
  ],
  "je_v_chranenom_uzemi": false,
  "dotknute_zivocichy_rastliny": [],
  "odkaz_enviroportal": null,
  "paragrafy": [
    {
      "paragraf": "82",
      "odsek": "7",
      "pismena": [],
      "zakon_nazov": "o ochrane prírody a krajiny",
      "zakon_cislo": "543/2002 Z. z."
    },
    {
      "paragraf": "47",
      "odsek": "3",
      "pismena": [],
      "zakon_nazov": "o ochrane prírody a krajiny",
      "zakon_cislo": "543/2002 Z. z."
    },
    {
      "paragraf": "82",
      "odsek": "3",
      "pismena": [],
      "zakon_nazov": "o ochrane prírody a krajiny",
      "zakon_cislo": "543/2002 Z. z."
    }
  ],
  "zhrnutie": "Dokument informuje o začatí správneho konania pre vydanie súhlasu na výrub 6 ks drevín na parcele E-KN č. 6283 v katastrálnom území Klenovec (okres Rimavská Sobota). Dôvodom je čistenie pozemku od náletových drevín. Záujemcovia o účasť v konaní majú lehotu 5 pracovných dní od zverejnenia informácie."
}