{
  "cislo_konania_spisu": "OU-KE-OSZP1-2025/015324-022",
  "cislo_rozhodnutia": null,
  "datum_dokumentu": "2025-05-29",
  "datum_zverejnenia": null,
  "lehoty_na_vyjadrenie": "Neuvedené",
  "ziadatel_navrhovatel": "Slovenská správa ciest",
  "miesto_realizacie": {
    "kraj": "Košický a Prešovský",
    "okres": "Michalovce a Humenné",
    "obec": "Strážske",
    "katastralne_uzemia": [
      {
        "nazov": "Strážske",
        "parcely": []
      },
      {
        "nazov": "Voľa",
        "parcely": []
      },
      {
        "nazov": "Nacina Ves",
        "parcely": []
      },
      {
        "nazov": "Petrovce nad Laborcom",
        "parcely": []
      },
      {
        "nazov": "Topoľany",
        "parcely": []
      },
      {
        "nazov": "Brekov",
        "parcely": []
      }
    ],
    "nazov_lokality": null
  },
  "typ_dokumentu": "Záväzné stanovisko zo zisťovacieho konania",
  "typ_zasahu": [
    "rekonštrukcia cesty",
    "výstavba preložky cesty",
    "výrub drevín",
    "výstavba mostných objektov",
    "preložky inžinierskych sietí"
  ],
  "typ_uzemia": [
    "1. stupeň ochrany"
  ],
  "je_v_chranenom_uzemi": true,
  "dotknute_zivocichy_rastliny": [
    "nelsená drevinná vegetácia",
    "náletové porasty",
    "brehové porasty",
    "ichtyofauna",
    "bentická fauna"
  ],
  "odkaz_enviroportal": "https://www.enviroportal.sk/eia/detail/i-18-nizny-hrabovec-petrovce-n-laborcom-prelozka-i-etapa-i-18-i-74-str-1",
  "zhrnutie": "Záväzné stanovisko EIA k zmene navrhovanej činnosti (preložka a rekonštrukcia ciest I/18 a I/74) v okresoch Michalovce a Humenné. Dokument určuje, že činnosť sa nebude posudzovať podľa zákona o EIA. Územie je v 1. stupni ochrany prírody a mimo vyšších chránených území. Spomínajú sa výruby drevín a vplyvy na vegetáciu pri potokoch."
}