{
  "cislo_konania_spisu": "OU-BA-OSZP3-2025/527079/MAA",
  "cislo_rozhodnutia": null,
  "datum_dokumentu": "2025-10-03",
  "datum_zverejnenia": "2025-10-06",
  "lehoty_na_vyjadrenie": "5 pracovných dní od zverejnenia upovedomenia o podaní žiadosti na elektronickom sídle správneho orgánu",
  "ziadatel_navrhovatel": "KPRHT, s. r. o.",
  "miesto_realizacie": {
    "kraj": "Bratislavský kraj",
    "okres": "Bratislava",
    "obec": "Devín",
    "katastralne_uzemia": [
      {
        "nazov": "Devín",
        "parcely": []
      }
    ],
    "nazov_lokality": "extravilán katastrálneho územia Devín"
  },
  "typ_dokumentu": "Oznámenie o začatí konania",
  "typ_zasahu": [
    "umiestnenie prenosného elektronického zariadenia",
    "elektrický ohradník"
  ],
  "typ_uzemia": [
    "2. stupeň ochrany"
  ],
  "je_v_chranenom_uzemi": true,
  "dotknute_zivocichy_rastliny": [],
  "odkaz_enviroportal": null,
  "paragrafy": [
    {
      "paragraf": "82",
      "odsek": "7",
      "pismena": [],
      "zakon_nazov": "o ochrane prírody a krajiny",
      "zakon_cislo": "543/2002 Z. z."
    },
    {
      "paragraf": "2",
      "odsek": "1",
      "pismena": [],
      "zakon_nazov": "o ochrane prírody a krajiny",
      "zakon_cislo": "543/2002 Z. z."
    },
    {
      "paragraf": "82",
      "odsek": "3",
      "pismena": [],
      "zakon_nazov": "o ochrane prírody a krajiny",
      "zakon_cislo": "543/2002 Z. z."
    },
    {
      "paragraf": "82",
      "odsek": "6",
      "pismena": [],
      "zakon_nazov": "o ochrane prírody a krajiny",
      "zakon_cislo": "543/2002 Z. z."
    },
    {
      "paragraf": "13",
      "odsek": "2",
      "pismena": [
        "l"
      ],
      "zakon_nazov": "o ochrane prírody a krajiny",
      "zakon_cislo": "543/2002 Z. z."
    }
  ],
  "zhrnutie": "Dokument predstavuje oznámenie o začatí správneho konania týkajúceho sa žiadosti spoločnosti KPRHT, s. r. o., o vydanie súhlasu na umiestnenie prenosného elektronického zariadenia (elektrického ohradníka) v extraviláne katastrálneho územia Devín. Navrhovaná činnosť sa má realizovať na území, kde platí druhý stupeň ochrany podľa zákona o ochrane prírody a krajiny. Verejnosť má 5 pracovných dní od zverejnenia na vyjadrenie záujmu byť účastníkom konania."
}