{
  "cislo_konania_spisu": "OU-BB-OSZP3-2025/016833-004",
  "cislo_rozhodnutia": null,
  "datum_dokumentu": "2025-05-13",
  "datum_zverejnenia": null,
  "lehoty_na_vyjadrenie": "v lehote do 5 dní odo dňa doručenia tohto upovedomenia",
  "ziadatel_navrhovatel": "Mesto Banská Bystrica",
  "miesto_realizacie": {
    "kraj": null,
    "okres": "Banská Bystrica",
    "obec": "Banská Bystrica",
    "katastralne_uzemia": [
      {
        "nazov": "Banská Bystrica",
        "parcely": [
          {
            "typ": "C-KN",
            "cisla": [
              "1931/1"
            ]
          }
        ]
      }
    ],
    "nazov_lokality": "Hečkovej ulici"
  },
  "typ_dokumentu": "Upovedomenie k podkladom rozhodnutia",
  "typ_zasahu": [
    "nakladanie s odpadmi - staré vozidlá"
  ],
  "typ_uzemia": [],
  "je_v_chranenom_uzemi": false,
  "dotknute_zivocichy_rastliny": [],
  "odkaz_enviroportal": null,
  "zhrnutie": "Verejná vyhláška informujúca o možnosti vyjadriť sa k podkladom pre rozhodnutie o tom, že vozidlo (Škoda Favorit) odstránené z Hečkovej ulice, parcela KN-C 1931/1, k.ú. Banská Bystrica, sa stáva odpadom (staré vozidlo). Účastníci konania majú na vyjadrenie 5 dní od doručenia upovedomenia. Dokument sa netýka chránených území ani konkrétnych druhov."
}