{
  "cislo_konania_spisu": "OU-LM-OSZP-2025/13869-Lo",
  "cislo_rozhodnutia": null,
  "datum_dokumentu": "2025-09-18",
  "datum_zverejnenia": null,
  "lehoty_na_vyjadrenie": "do 5 pracovných dní od zverejnenia tohto oznámenia potvrdiť písomnou formou záujem byť zúčastnenou osobou v uvedenom správnom konaní",
  "ziadatel_navrhovatel": "Andrej Kováč",
  "miesto_realizacie": {
    "kraj": null,
    "okres": "Liptovský Mikuláš",
    "obec": "Nižná Boca",
    "katastralne_uzemia": [
      {
        "nazov": "Nižná Boca",
        "parcely": [
          {
            "typ": "KN-C",
            "cisla": [
              "1596/39"
            ]
          }
        ]
      }
    ],
    "nazov_lokality": null
  },
  "typ_dokumentu": "Oznámenie o začatí konania",
  "typ_zasahu": [
    "výrub drevín"
  ],
  "typ_uzemia": [
    "neviem"
  ],
  "je_v_chranenom_uzemi": null,
  "dotknute_zivocichy_rastliny": [],
  "odkaz_enviroportal": null,
  "paragrafy": [
    {
      "paragraf": "47",
      "odsek": "3",
      "pismena": [],
      "nazov": "o ochrane prírody a krajiny",
      "cislo": "543/2002"
    },
    {
      "paragraf": "82",
      "odsek": "7",
      "pismena": [],
      "nazov": null,
      "cislo": "543/2002"
    }
  ],
  "zhrnutie": "Dokument je oznámením o začatí konania na žiadosť Andreja Kováča o výrub 4 kusov drevín v katastrálnom území Nižná Boca, okres Liptovský Mikuláš, na parcele č. KN-C 1596/39. Dôvodom výrubu je zlý zdravotný stav drevín a ohrozenie nehnuteľnosti. Záujem byť zúčastnenou osobou v konaní je potrebné potvrdiť do 5 pracovných dní od zverejnenia."
}
