{
  "cislo_konania_spisu": "OU-PP-OSZP-2025/034327",
  "cislo_rozhodnutia": null,
  "datum_dokumentu": "2025-09-25",
  "datum_zverejnenia": "2025-01-06",
  "lehoty_na_vyjadrenie": "5 pracovných dní od zverejnenia",
  "ziadatel_navrhovatel": "TECH – MONT Helicopter company s.r.o.",
  "miesto_realizacie": {
    "kraj": null,
    "okres": "Poprad",
    "obec": null,
    "katastralne_uzemia": [],
    "nazov_lokality": null
  },
  "typ_dokumentu": "Upovedomenie o začatí správneho konania",
  "typ_zasahu": [
    "prelet lietajúcim športovým zariadením"
  ],
  "typ_uzemia": [
    "Tretí stupeň ochrany"
  ],
  "je_v_chranenom_uzemi": true,
  "dotknute_zivocichy_rastliny": [],
  "odkaz_enviroportal": null,
  "paragrafy": [
    {
      "paragraf": "82",
      "odsek": "7",
      "pismena": [],
      "zakon_nazov": "o ochrane prírody a krajiny",
      "zakon_cislo": "543/2002 Z. z."
    },
    {
      "paragraf": "14",
      "odsek": "2",
      "pismena": [
        "d"
      ],
      "zakon_nazov": "o ochrane prírody a krajiny",
      "zakon_cislo": "543/2002"
    }
  ],
  "zhrnutie": "Okresný úrad Poprad upovedomuje o začatí správneho konania pre žiadosť spoločnosti TECH – MONT Helicopter company s.r.o. o súhlas na prelet lietajúcim športovým zariadením v územiach s tretím stupňom ochrany. Lehota na potvrdenie záujmu byť účastníkom konania je 5 pracovných dní od zverejnenia."
}