{
  "cislo_konania_spisu": null,
  "cislo_rozhodnutia": null,
  "datum_dokumentu": "2025-05-07",
  "datum_zverejnenia": null,
  "lehoty_na_vyjadrenie": "do 15 dní odo dňa zverejnenia dotknutou obcou",
  "ziadatel_navrhovatel": "Obec Dvorníky",
  "miesto_realizacie": {
    "kraj": null,
    "okres": "Hlohovec",
    "obec": "Dvorníky",
    "katastralne_uzemia": [],
    "nazov_lokality": null
  },
  "typ_dokumentu": "Informácia pre verejnosť",
  "typ_zasahu": [
    "strategický dokument - územné plánovanie"
  ],
  "typ_uzemia": [
    "neviem"
  ],
  "je_v_chranenom_uzemi": false,
  "dotknute_zivocichy_rastliny": [],
  "odkaz_enviroportal": null,
  "zhrnutie": "Informácia pre verejnosť o predložení oznámenia o strategickom dokumente Územný plán obce Dvorníky – Zmeny a doplnky č. 3 žiadateľom Obec Dvorníky. Verejnosť môže predkladať stanoviská do 15 dní od zverejnenia obcou."
}