{
  "cislo_konania_spisu": "OU-IL-OSZP-2025/000679-008",
  "cislo_rozhodnutia": null,
  "datum_dokumentu": "2025-06-04",
  "datum_zverejnenia": null,
  "lehoty_na_vyjadrenie": "najneskoršie na ústnom pojednávaní dňa 11. 07. 2025",
  "ziadatel_navrhovatel": "Útes 2, s.r.o.",
  "miesto_realizacie": {
    "kraj": null,
    "okres": "Ilava",
    "obec": "Slavnica",
    "katastralne_uzemia": [
      {
        "nazov": "Slavnica",
        "parcely": [
          {
            "typ": "C-KN",
            "cisla": [
              "495/16",
              "495/32",
              "495/76",
              "495/77",
              "495/78",
              "495/79",
              "495/80",
              "495/81",
              "495/82"
            ]
          }
        ]
      }
    ],
    "nazov_lokality": "Slavnica - Hornovec"
  },
  "typ_dokumentu": "Oznámenie o začatí stavebného konania (Verejná vyhláška)",
  "typ_zasahu": [
    "výstavba vodnej stavby",
    "výstavba vodovodu",
    "výstavba prípojok vody"
  ],
  "typ_uzemia": [
    "neviem"
  ],
  "je_v_chranenom_uzemi": false,
  "dotknute_zivocichy_rastliny": [],
  "odkaz_enviroportal": null,
  "zhrnutie": "Verejná vyhláška oznamuje začatie stavebného konania pre vodnú stavbu Technická infraštruktúra, Slavnica - Hornovec v obci Slavnica, Okres Ilava. Ide o predĺženie verejného vodovodu a prípojky vody. Ústne pojednávanie je nariadené na 11.07.2025. Dokument nespomína dotknuté chránené územia ani druhy."
}