{
  "cislo_konania_spisu": "OU-TT-OSZP3-2025/034038-015",
  "cislo_rozhodnutia": "OU-TT-OSZP3-2025/034038-0189411/2025",
  "datum_dokumentu": "2025-10-29",
  "datum_zverejnenia": null,
  "lehoty_na_vyjadrenie": "do 15 dní od jeho doručenia (odvolanie)",
  "ziadatel_navrhovatel": "KARPATKY, s.r.o.",
  "miesto_realizacie": {
    "kraj": "Trnavský",
    "okres": "Trnava",
    "obec": "Dlhá",
    "katastralne_uzemia": [
      {
        "nazov": "Dlhá",
        "parcely": [
          {
            "typ": "C",
            "cisla": [
              "1121/40"
            ]
          }
        ]
      }
    ],
    "nazov_lokality": "Obytná zóna Dlhá"
  },
  "typ_dokumentu": "Povolenie na užívanie vodnej stavby",
  "typ_zasahu": [
    "výstavba vodnej stavby",
    "výstavba kanalizácie",
    "vsakovanie vôd"
  ],
  "typ_uzemia": [
    "neviem"
  ],
  "je_v_chranenom_uzemi": null,
  "dotknute_zivocichy_rastliny": [],
  "odkaz_enviroportal": null,
  "paragrafy": [
    {
      "paragraf": "5",
      "odsek": "1",
      "pismena": [],
      "zakon_nazov": "o štátnej správe starostlivosti o životné prostredie a o zmene a doplnení niektorých zákonov",
      "zakon_cislo": "525/2003 Z. z."
    },
    {
      "paragraf": "61",
      "odsek": null,
      "pismena": [],
      "zakon_nazov": "o vodách a o zmene zákona SNR č. 372/1990 Zb. o priestupkoch",
      "zakon_cislo": "364/2004 Z. z."
    },
    {
      "paragraf": "120",
      "odsek": null,
      "pismena": [],
      "zakon_nazov": "o územnom plánovaní a stavebnom poriadku",
      "zakon_cislo": "50/1976 Zb."
    },
    {
      "paragraf": null,
      "odsek": null,
      "pismena": [],
      "zakon_nazov": "o správnom konaní",
      "zakon_cislo": "71/1967 Zb."
    },
    {
      "paragraf": "26",
      "odsek": "3",
      "pismena": [],
      "zakon_nazov": "o vodách a o zmene zákona SNR č. 372/1990 Zb. o priestupkoch",
      "zakon_cislo": "364/2004 Z. z."
    },
    {
      "paragraf": "76",
      "odsek": null,
      "pismena": [],
      "zakon_nazov": "o územnom plánovaní a stavebnom poriadku",
      "zakon_cislo": "50/1976 Zb."
    },
    {
      "paragraf": "81",
      "odsek": null,
      "pismena": [],
      "zakon_nazov": "o územnom plánovaní a stavebnom poriadku",
      "zakon_cislo": "50/1976 Zb."
    },
    {
      "paragraf": "82",
      "odsek": null,
      "pismena": [],
      "zakon_nazov": "o územnom plánovaní a stavebnom poriadku",
      "zakon_cislo": "50/1976 Zb."
    },
    {
      "paragraf": "81",
      "odsek": "4",
      "pismena": [],
      "zakon_nazov": "o územnom plánovaní a stavebnom poriadku",
      "zakon_cislo": "50/1976 Zb."
    },
    {
      "paragraf": null,
      "odsek": null,
      "pismena": [
        "g"
      ],
      "zakon_nazov": "o správnych poplatkoch",
      "zakon_cislo": "145/1995 Z. z."
    },
    {
      "paragraf": null,
      "odsek": null,
      "pismena": [],
      "zakon_nazov": "ktorým sa menia a dopĺňajú zákony v pôsobnosti Ministerstva financií SR v súvislosti so zavedením meny euro v Slovenskej republike",
      "zakon_cislo": "465/2008 Z. z."
    },
    {
      "paragraf": "84",
      "odsek": "5",
      "pismena": [],
      "zakon_nazov": "Stavebný zákon a o zmene a doplnení niektorých zákonov",
      "zakon_cislo": "25/2025 Z. z."
    },
    {
      "paragraf": "53",
      "odsek": null,
      "pismena": [],
      "zakon_nazov": "o správnom konaní",
      "zakon_cislo": "71/1967 Zb."
    },
    {
      "paragraf": "54",
      "odsek": "1",
      "pismena": [],
      "zakon_nazov": "o správnom konaní",
      "zakon_cislo": "71/1967 Zb."
    },
    {
      "paragraf": "54",
      "odsek": "2",
      "pismena": [],
      "zakon_nazov": "o správnom konaní",
      "zakon_cislo": "71/1967 Zb."
    },
    {
      "paragraf": "61",
      "odsek": "4",
      "pismena": [],
      "zakon_nazov": "o územnom plánovaní a stavebnom poriadku",
      "zakon_cislo": "50/1976 Zb."
    },
    {
      "paragraf": "3",
      "odsek": "2",
      "pismena": [],
      "zakon_nazov": "o verejných vodovodoch a verejných kanalizáciách a o zmene a doplnení zákona č. 276/2001 Z. z. o regulácii v sieťových odvetviach",
      "zakon_cislo": "442/2002 Z. z."
    },
    {
      "paragraf": "9",
      "odsek": "2",
      "pismena": [
        "a"
      ],
      "zakon_nazov": null,
      "zakon_cislo": "272/2016 Z. z."
    }
  ],
  "zhrnutie": "Okresný úrad Trnava vydal povolenie na trvalé užívanie vodnej stavby 'SO 03 Areálová dažďová kanalizácia z komunikácií' pre žiadateľa KARPATKY, s.r.o. Realizácia prebieha v obci Dlhá, katastrálnom území Dlhá, v rámci lokality 'Obytná zóna Dlhá' a zahŕňa výstavbu dažďovej kanalizácie a vsakovacieho systému pre odvádzanie vôd z povrchového odtoku.",
  "zasiahnute_chranene_uzemia": {}
}