{
  "cislo_konania_spisu": null,
  "cislo_rozhodnutia": null,
  "datum_dokumentu": "2019",
  "datum_zverejnenia": null,
  "lehoty_na_vyjadrenie": null,
  "ziadatel_navrhovatel": "SLOVENSKÁ AGENTÚRA ŽIVOTNÉHO PROSTREDIA",
  "miesto_realizacie": {
    "kraj": null,
    "okres": "Pezinok",
    "obec": null,
    "katastralne_uzemia": [],
    "nazov_lokality": "okres Pezinok"
  },
  "typ_dokumentu": "Štúdia RÚSES (mapový výstup)",
  "typ_zasahu": [],
  "typ_uzemia": [],
  "je_v_chranenom_uzemi": null,
  "dotknute_zivocichy_rastliny": [],
  "odkaz_enviroportal": null,
  "paragrafy": [],
  "zhrnutie": "Tento dokument predstavuje mapový výstup a legendu k štúdii Regionálnych územných systémov ekologickej stability (RÚSES) pre okres Pezinok z roku 2019. Štúdia bola spracovaná pre potreby vytvorenia základnej východiskovej bázy pre reguláciu návrhu budovania zelenej infraštruktúry, pričom identifikuje a klasifikuje rôzne krajinné štruktúry a prvky v rámci okresu Pezinok. Objednávateľom projektu bola Slovenská agentúra životného prostredia."
}