{
  "cislo_konania_spisu": "OU-BJ-OSZP-2025/011514-0043175/2025",
  "cislo_rozhodnutia": null,
  "datum_dokumentu": "2025-10-09",
  "datum_zverejnenia": "2025-10-09",
  "lehoty_na_vyjadrenie": "najneskoršie pri ústnom pojednávaní dňa 27.11.2024 o 09:00 hod.",
  "ziadatel_navrhovatel": "Východoslovenská vodárenská spoločnosť, a.s., Komenského 50, 042 48 Košice",
  "miesto_realizacie": {
    "kraj": null,
    "okres": "Bardejov",
    "obec": "Osikov",
    "katastralne_uzemia": [
      {
        "nazov": "Osikov",
        "parcely": [
          {
            "typ": "C-KN",
            "cisla": [
              "554",
              "679/3",
              "679/4",
              "562/21",
              "390/3",
              "387/3",
              "562/22",
              "358/3",
              "562/23",
              "562/24",
              "562/43",
              "562/46",
              "562/47",
              "562/48",
              "562/44",
              "562/45"
            ]
          },
          {
            "typ": "E-KN",
            "cisla": [
              "307/1",
              "383/1"
            ]
          }
        ]
      }
    ],
    "nazov_lokality": "rozšírenie vodovodu za farou"
  },
  "typ_dokumentu": "Oznámenie o začatí konania / Verejná vyhláška",
  "typ_zasahu": [
    "užívanie vodnej stavby",
    "rozšírenie vodovodu"
  ],
  "typ_uzemia": [],
  "je_v_chranenom_uzemi": null,
  "dotknute_zivocichy_rastliny": [],
  "odkaz_enviroportal": null,
  "paragrafy": [
    {
      "paragraf": "58",
      "odsek": null,
      "pismena": [
        "c"
      ],
      "zakon_nazov": "vodný zákon",
      "zakon_cislo": "364/2004 Z. z."
    },
    {
      "paragraf": "61",
      "odsek": null,
      "pismena": [
        "a"
      ],
      "zakon_nazov": "vodný zákon",
      "zakon_cislo": "364/2004 Z. z."
    },
    {
      "paragraf": "71",
      "odsek": null,
      "pismena": [],
      "zakon_nazov": "vodný zákon",
      "zakon_cislo": "364/2004 Z. z."
    },
    {
      "paragraf": "5",
      "odsek": null,
      "pismena": [],
      "zakon_nazov": "o štátnej správe starostlivosti o životné prostredie",
      "zakon_cislo": "525/2003 Z. z."
    },
    {
      "paragraf": "2",
      "odsek": "3",
      "pismena": [],
      "zakon_nazov": "o organizácii miestnej štátnej správy",
      "zakon_cislo": "180/2013 Z. z."
    },
    {
      "paragraf": "3",
      "odsek": "1",
      "pismena": [
        "e"
      ],
      "zakon_nazov": "o organizácii miestnej štátnej správy",
      "zakon_cislo": "180/2013 Z. z."
    },
    {
      "paragraf": "16",
      "odsek": "1",
      "pismena": [],
      "zakon_nazov": "Stavebný zákon",
      "zakon_cislo": "25/2025 Z. z."
    },
    {
      "paragraf": "84",
      "odsek": "5",
      "pismena": [],
      "zakon_nazov": "Stavebný zákon",
      "zakon_cislo": "25/2025 Z. z."
    },
    {
      "paragraf": "120",
      "odsek": null,
      "pismena": [],
      "zakon_nazov": "o územnom plánovaní a stavebnom poriadku",
      "zakon_cislo": "50/1976 Zb."
    },
    {
      "paragraf": "61",
      "odsek": null,
      "pismena": [
        "c"
      ],
      "zakon_nazov": "vodný zákon",
      "zakon_cislo": "364/2004 Z. z."
    },
    {
      "paragraf": "26",
      "odsek": "3",
      "pismena": [],
      "zakon_nazov": "vodný zákon",
      "zakon_cislo": "364/2004 Z. z."
    },
    {
      "paragraf": "80",
      "odsek": null,
      "pismena": [],
      "zakon_nazov": "o územnom plánovaní a stavebnom poriadku",
      "zakon_cislo": "50/1976 Zb."
    },
    {
      "paragraf": "73",
      "odsek": "1",
      "pismena": [],
      "zakon_nazov": "vodný zákon",
      "zakon_cislo": "364/2004 Z. z."
    },
    {
      "paragraf": "73",
      "odsek": "5",
      "pismena": [],
      "zakon_nazov": "vodný zákon",
      "zakon_cislo": "364/2004 Z. z."
    },
    {
      "paragraf": "73",
      "odsek": "6",
      "pismena": [],
      "zakon_nazov": "vodný zákon",
      "zakon_cislo": "364/2004 Z. z."
    },
    {
      "paragraf": "18",
      "odsek": null,
      "pismena": [],
      "zakon_nazov": "o správnom konaní",
      "zakon_cislo": "71/1967 Zb."
    },
    {
      "paragraf": "26",
      "odsek": "1",
      "pismena": [],
      "zakon_nazov": "o správnom konaní",
      "zakon_cislo": "71/1967 Zb."
    }
  ],
  "zhrnutie": "Tento dokument je verejnou vyhláškou oznamujúcou začatie konania o povolenie užívania časti vodnej stavby „SO 02 Zásobovanie vodou“, ktorá je súčasťou rozšírenia vodovodu v katastrálnom území Osikov, okres Bardejov. Žiadateľom je Východoslovenská vodárenská spoločnosť, a.s. Ústne pojednávanie spojené s miestnym zisťovaním sa uskutoční dňa 27.11.2024 (pravdepodobne 2025) a námietky je možné uplatniť najneskoršie pri tomto pojednávaní. Dokument nespomína žiadne chránené územia ani druhy."
}
